jsonfactory/__init__.py
jsonfactory/decorators.py
jsonfactory/registry.py
json_object_factory-0.0.2.dist-info/top_level.txt
json_object_factory-0.0.2.dist-info/METADATA
json_object_factory-0.0.2.dist-info/DESCRIPTION.rst
json_object_factory-0.0.2.dist-info/metadata.json
json_object_factory-0.0.2.dist-info/WHEEL
json_object_factory-0.0.2.dist-info/RECORD
