Metadata-Version: 2.0
Name: json-object-factory
Version: 0.0.2
Summary: Simplify JSON Encoders and Object Hooks
Home-page: https://github.com/nocarryr/json-object-factory
Author: Matthew Reid
Author-email: matt@nomadic-recording.com
License: MIT
Keywords: json
Platform: any
Classifier: Development Status :: 3 - Alpha
Classifier: Intended Audience :: Developers
Classifier: License :: OSI Approved :: MIT License
Classifier: Operating System :: OS Independent
Classifier: Programming Language :: Python
Classifier: Topic :: Software Development
Classifier: Programming Language :: Python :: 2
Classifier: Programming Language :: Python :: 2.7
Classifier: Programming Language :: Python :: 3
Classifier: Programming Language :: Python :: 3.4
Classifier: Programming Language :: Python :: 3.5
